{
  "instance_id": "sympy__sympy-16281",
  "repo": "sympy/sympy",
  "repo_url": "https://github.com/sympy/sympy.git",
  "base_commit": "41490b75f3621408e0468b0e7b6dc409601fc6ff",
  "sample_dir": "D:\\Projects\\COMP691\\FlowGraphGen\\data\\sympy_sympy-16281",
  "patch_file": "D:\\Projects\\COMP691\\FlowGraphGen\\data\\sympy_sympy-16281\\patch.diff",
  "problem_statement_file": "D:\\Projects\\COMP691\\FlowGraphGen\\data\\sympy_sympy-16281\\problem_statement.txt",
  "original_dir": "D:\\Projects\\COMP691\\FlowGraphGen\\data\\sympy_sympy-16281\\original",
  "patched_dir": "D:\\Projects\\COMP691\\FlowGraphGen\\data\\sympy_sympy-16281\\patched",
  "apply_log_file": "D:\\Projects\\COMP691\\FlowGraphGen\\data\\sympy_sympy-16281\\apply_patch.log",
  "problem_statement": "Product pretty print could be improved\nThis is what the pretty printing for `Product` looks like:\r\n\r\n```\r\n>>> pprint(Product(1, (n, 1, oo)))\r\n  ∞\r\n┬───┬\r\n│   │ 1\r\n│   │\r\nn = 1\r\n>>> pprint(Product(1/n, (n, 1, oo)))\r\n   ∞\r\n┬──────┬\r\n│      │ 1\r\n│      │ ─\r\n│      │ n\r\n│      │\r\n n = 1\r\n>>> pprint(Product(1/n**2, (n, 1, oo)))\r\n    ∞\r\n┬────────┬\r\n│        │ 1\r\n│        │ ──\r\n│        │  2\r\n│        │ n\r\n│        │\r\n  n = 1\r\n>>> pprint(Product(1, (n, 1, oo)), use_unicode=False)\r\n  oo\r\n_____\r\n|   | 1\r\n|   |\r\nn = 1\r\n>>> pprint(Product(1/n, (n, 1, oo)), use_unicode=False)\r\n   oo\r\n________\r\n|      | 1\r\n|      | -\r\n|      | n\r\n|      |\r\n n = 1\r\n>>> pprint(Product(1/n**2, (n, 1, oo)), use_unicode=False)\r\n    oo\r\n__________\r\n|        | 1\r\n|        | --\r\n|        |  2\r\n|        | n\r\n|        |\r\n  n = 1\r\n```\r\n\r\n(if those don't look good in your browser copy paste them into the terminal)\r\n\r\nThis could be improved:\r\n\r\n- Why is there always an empty line at the bottom of the ∏? Keeping everything below the horizontal line is good, but the bottom looks asymmetric, and it makes the ∏ bigger than it needs to be.\r\n\r\n- The ∏ is too fat IMO. \r\n\r\n- It might look better if we extended the top bar. I'm unsure about this. \r\n\r\nCompare this\r\n\r\n```\r\n    ∞\r\n─┬─────┬─\r\n │     │  1\r\n │     │  ──\r\n │     │   2\r\n │     │  n\r\n  n = 1\r\n```\r\n\r\nThat's still almost twice as wide as the equivalent Sum, but if you make it much skinnier it starts to look bad.\r\n\r\n```\r\n  ∞\r\n ____\r\n ╲\r\n  ╲   1\r\n   ╲  ──\r\n   ╱   2\r\n  ╱   n\r\n ╱\r\n ‾‾‾‾\r\nn = 1\r\n```\n",
  "changed_files": "[\"sympy/printing/pretty/pretty.py\"]",
  "original_files_saved": "[\"sympy/printing/pretty/pretty.py\"]",
  "patched_files_saved": "[\"sympy/printing/pretty/pretty.py\"]",
  "status": "applied"
}